chat-ui/README.md
chat-ui/frontend/404.html
chat-ui/frontend/favicon.ico
chat-ui/frontend/index.html
chat-ui/frontend/_next/data/qInvqPM7B0JkvRh9PQZ8l/index.json
chat-ui/frontend/_next/static/chunks/105-4bc220fcbf235939.js
chat-ui/frontend/_next/static/chunks/542b50fd-07ebedc579cef971.js
chat-ui/frontend/_next/static/chunks/framework-73b8966a3c579ab0.js
chat-ui/frontend/_next/static/chunks/main-6260d066cf2cd7b1.js
chat-ui/frontend/_next/static/chunks/polyfills-c67a75d1b6f99dc8.js
chat-ui/frontend/_next/static/chunks/webpack-59c5c889f52620d6.js
chat-ui/frontend/_next/static/chunks/pages/_app-8a052ace6c8c1dc7.js
chat-ui/frontend/_next/static/chunks/pages/_error-3f6d1c55bb8051ab.js
chat-ui/frontend/_next/static/chunks/pages/index-a3c8b6112055b18c.js
chat-ui/frontend/_next/static/css/e1b03755feecbabd.css
chat-ui/frontend/_next/static/media/2aaf0723e720e8b9-s.p.woff2
chat-ui/frontend/_next/static/media/9c4f34569c9b36ca-s.woff2
chat-ui/frontend/_next/static/media/ae9ae6716d4f8bf8-s.woff2
chat-ui/frontend/_next/static/media/b1db3e28af9ef94a-s.woff2
chat-ui/frontend/_next/static/media/b967158bc7d7a9fb-s.woff2
chat-ui/frontend/_next/static/media/c0f5ec5bbf5913b7-s.woff2
chat-ui/frontend/_next/static/media/d1d9458b69004127-s.woff2
chat-ui/frontend/_next/static/qInvqPM7B0JkvRh9PQZ8l/_buildManifest.js
chat-ui/frontend/_next/static/qInvqPM7B0JkvRh9PQZ8l/_ssgManifest.js
chat-ui/frontend/static/bot-avatar.png
chat-ui/frontend/static/user-avatar.png
examples/README.md
examples/demo_chain_as_action.py
examples/demo_chain_with_guardrails.py
examples/execution_rails/README.md
examples/execution_rails/img/math_question.PNG
examples/execution_rails/img/simple_conversation.PNG
examples/execution_rails/sample_rails/config.yml
examples/execution_rails/sample_rails/math.co
examples/grounding_rail/README.md
examples/grounding_rail/factcheck.co
examples/grounding_rail/general.co
examples/grounding_rail/hallucination.co
examples/grounding_rail/llm_config.yaml
custom_guardrails-0.1.0.dist-info/LICENCES-3rd-party
custom_guardrails-0.1.0.dist-info/LICENSE-Apache-2.0.txt
custom_guardrails-0.1.0.dist-info/LICENSE.md
custom_guardrails-0.1.0.dist-info/METADATA
custom_guardrails-0.1.0.dist-info/WHEEL
custom_guardrails-0.1.0.dist-info/entry_points.txt
custom_guardrails-0.1.0.dist-info/top_level.txt
custom_guardrails-0.1.0.dist-info/RECORD
